{
  "db_name": "PostgreSQL",
  "query": "\n        SELECT asc_id, sid, public_key, scopes, not_before, not_after, signature\n        FROM id_asc\n        WHERE asc_id = $1\n        ",
  "describe": {
    "columns": [
      {
        "ordinal": 0,
        "name": "asc_id",
        "type_info": "Uuid"
      },
      {
        "ordinal": 1,
        "name": "sid",
        "type_info": "Text"
      },
      {
        "ordinal": 2,
        "name": "public_key",
        "type_info": "Bytea"
      },
      {
        "ordinal": 3,
        "name": "scopes",
        "type_info": "Jsonb"
      },
      {
        "ordinal": 4,
        "name": "not_before",
        "type_info": "Timestamptz"
      },
      {
        "ordinal": 5,
        "name": "not_after",
        "type_info": "Timestamptz"
      },
      {
        "ordinal": 6,
        "name": "signature",
        "type_info": "Bytea"
      }
    ],
    "parameters": {
      "Left": [
        "Uuid"
      ]
    },
    "nullable": [
      false,
      false,
      false,
      false,
      false,
      false,
      false
    ]
  },
  "hash": "6c31422e7f862dfb306f85f11719733545ceecdd5272194cb20a6f6351658e19"
}
